slicevis/__init__.py
slicevis/image.py
slicevis/load.py
slicevis/widget.py
slicevis-1.0.0.dist-info/LICENSE
slicevis-1.0.0.dist-info/METADATA
slicevis-1.0.0.dist-info/WHEEL
slicevis-1.0.0.dist-info/top_level.txt
slicevis-1.0.0.dist-info/RECORD
