Metadata-Version: 2.1
Name: slicevis
Version: 1.0.0
Summary: A package for interactive slice visualization.
Home-page: https://git.rwth-aachen.de/nicholasbook/sce-project-ss22
Author: Nicholas Book
Author-email: nicholas.book@rwth-aachen.de
License: MIT
Classifier: Programming Language :: Python :: 3
Classifier: License :: OSI Approved :: MIT License
Requires-Python: >=3.8
License-File: LICENSE
Requires-Dist: numpy
Requires-Dist: pygff
Requires-Dist: nibabel
Requires-Dist: matplotlib
Requires-Dist: plotly
Requires-Dist: ipywidgets
Requires-Dist: nbformat (>=4.2.0)
Requires-Dist: wheel
Requires-Dist: pandas
